pysr_abc_http_message/__init__.py
pysr_abc_http_message/file.py
pysr_abc_http_message/message.py
pysr_abc_http_message/request.py
pysr_abc_http_message/response.py
pysr_abc_http_message/server_request.py
pysr_abc_http_message/stream.py
pysr_abc_http_message/uri.py
pysr_abc_http_message-1.0.0.dist-info/METADATA
pysr_abc_http_message-1.0.0.dist-info/WHEEL
pysr_abc_http_message-1.0.0.dist-info/RECORD
